MANIFEST.in
README.md
setup.py
dash_scroll_up/__init__.py
dash_scroll_up/bundle.js
dash_scroll_up/metadata.json
dash_scroll_up/version.py
dash_scroll_up.egg-info/PKG-INFO
dash_scroll_up.egg-info/SOURCES.txt
dash_scroll_up.egg-info/dependency_links.txt
dash_scroll_up.egg-info/top_level.txt