Metadata-Version: 1.0
Name: dash-scroll-up
Version: 0.0.2
Summary: Dash component to add custom button to scroll to the top of the page.
Home-page: UNKNOWN
Author: martinbaste
Author-email: UNKNOWN
License: MIT
Platform: UNKNOWN
